README.md
setup.cfg
setup.py
ovrlib/__init__.py
ovrlib/__version__.py
ovrlib/exceptions.py
ovrlib/ga.py
ovrlib/pa.py
ovrlib/pa_scratch.py
ovrlib/wi.py
ovrlib.egg-info/PKG-INFO
ovrlib.egg-info/SOURCES.txt
ovrlib.egg-info/dependency_links.txt
ovrlib.egg-info/requires.txt
ovrlib.egg-info/top_level.txt