Metadata-Version: 2.1
Name: ovrlib
Version: 0.0.6
Summary: Library to interface with per-state online voter registration APIs
Home-page: https://github.com/vote/state-registration-apis
Author: Sage Weil
Author-email: sage@newdream.net
Maintainer: Sage Weil
Maintainer-email: sage@newdream.net
License: Apache 2.0
Keywords: python ovr vote
Platform: UNKNOWN
Classifier: Development Status :: 5 - Production/Stable
Classifier: License :: OSI Approved :: Apache Software License
Classifier: Intended Audience :: Developers
Classifier: Intended Audience :: System Administrators
Classifier: Operating System :: OS Independent
Classifier: Topic :: Internet :: WWW/HTTP
Classifier: Programming Language :: Python :: 3.5
Classifier: Programming Language :: Python :: 3.6
Classifier: Programming Language :: Python :: 3.7
Classifier: Programming Language :: Python :: 3.8
Classifier: Programming Language :: Python :: Implementation :: PyPy
